mcp_memory_service/__init__.py
mcp_memory_service/_version.py
mcp_memory_service/compat.py
mcp_memory_service/config.py
mcp_memory_service/dependency_check.py
mcp_memory_service/lm_studio_compat.py
mcp_memory_service/mcp_server.py
mcp_memory_service/offline_mode.py
mcp_memory_service/server_impl.py
mcp_memory_service/api/__init__.py
mcp_memory_service/api/client.py
mcp_memory_service/api/operations.py
mcp_memory_service/api/sync_wrapper.py
mcp_memory_service/api/types.py
mcp_memory_service/backup/__init__.py
mcp_memory_service/backup/scheduler.py
mcp_memory_service/cli/__init__.py
mcp_memory_service/cli/ingestion.py
mcp_memory_service/cli/main.py
mcp_memory_service/cli/utils.py
mcp_memory_service/consolidation/__init__.py
mcp_memory_service/consolidation/associations.py
mcp_memory_service/consolidation/base.py
mcp_memory_service/consolidation/clustering.py
mcp_memory_service/consolidation/compression.py
mcp_memory_service/consolidation/consolidator.py
mcp_memory_service/consolidation/decay.py
mcp_memory_service/consolidation/forgetting.py
mcp_memory_service/consolidation/health.py
mcp_memory_service/consolidation/relationship_inference.py
mcp_memory_service/consolidation/scheduler.py
mcp_memory_service/discovery/__init__.py
mcp_memory_service/discovery/client.py
mcp_memory_service/discovery/mdns_service.py
mcp_memory_service/embeddings/__init__.py
mcp_memory_service/embeddings/external_api.py
mcp_memory_service/embeddings/onnx_embeddings.py
mcp_memory_service/ingestion/__init__.py
mcp_memory_service/ingestion/base.py
mcp_memory_service/ingestion/chunker.py
mcp_memory_service/ingestion/csv_loader.py
mcp_memory_service/ingestion/json_loader.py
mcp_memory_service/ingestion/pdf_loader.py
mcp_memory_service/ingestion/registry.py
mcp_memory_service/ingestion/semtools_loader.py
mcp_memory_service/ingestion/text_loader.py
mcp_memory_service/models/__init__.py
mcp_memory_service/models/association.py
mcp_memory_service/models/memory.py
mcp_memory_service/models/ontology.py
mcp_memory_service-10.4.1.dist-info/METADATA
mcp_memory_service-10.4.1.dist-info/WHEEL
mcp_memory_service-10.4.1.dist-info/entry_points.txt
mcp_memory_service-10.4.1.dist-info/licenses/LICENSE
mcp_memory_service-10.4.1.dist-info/licenses/NOTICE
mcp_memory_service-10.4.1.dist-info/RECORD
